filterframework_to_nwb/__init__.py
filterframework_to_nwb/core.py
filterframework_to_nwb/fl_extension_helpers.py
filterframework_to_nwb/nspike_helpers.py
filterframework_to_nwb-0.1.0.dev0.dist-info/LICENSE
filterframework_to_nwb-0.1.0.dev0.dist-info/METADATA
filterframework_to_nwb-0.1.0.dev0.dist-info/WHEEL
filterframework_to_nwb-0.1.0.dev0.dist-info/entry_points.txt
filterframework_to_nwb-0.1.0.dev0.dist-info/top_level.txt
filterframework_to_nwb-0.1.0.dev0.dist-info/RECORD
